saml2art/__init__.py
saml2art/commands/__init__.py
saml2art/commands/configure.py
saml2art/commands/login.py
saml2art/commands/main.py
saml2art/config/__init__.py
saml2art/config/config.py
saml2art/exporter/__init__.py
saml2art/exporter/netrc.py
saml2art/idp/__init__.py
saml2art/idp/okta.py
saml2art/mfa/__init__.py
saml2art/mfa/duomfa.py
saml2art/utils/__init__.py
saml2art/utils/httputils.py
saml2art-0.0.6.dist-info/METADATA
saml2art-0.0.6.dist-info/WHEEL
saml2art-0.0.6.dist-info/entry_points.txt
saml2art-0.0.6.dist-info/top_level.txt
saml2art-0.0.6.dist-info/RECORD
