Metadata-Version: 2.1
Name: saml2art
Version: 0.0.6
Summary: CLI tool which enables you to login and retrieve Artifactory credentials using OKTA Identity Provider
Home-page: UNKNOWN
Author: Shlomi Benita
Author-email: 
License: UNKNOWN
Platform: UNKNOWN
Classifier: Intended Audience :: Developers
Classifier: Topic :: Software Development :: Build Tools
Classifier: Programming Language :: Python :: 3.7
Requires-Python: >=3.7
Requires-Dist: requests (>=2.23.0)
Requires-Dist: argparse-prompt (>=0.0.4)
Requires-Dist: lxml (>=4.5.0)
Requires-Dist: keyring (>=21.2.1)
